{
"type": "FeatureCollection",
"name": "panama",
"crs": { "type": "name", "properties": { "name": "urn:ogc:def:crs:OGC:1.3:CRS84" } },
"features": [
{ "type": "Feature", "properties": { "field_1": 772651.9843, "field_2": 994513.0273 }, "geometry": { "type": "Point", "coordinates": [ -78.520225276598012, 8.988590349237342 ] } },
{ "type": "Feature", "properties": { "field_1": 772654.2524, "field_2": 994507.13 }, "geometry": { "type": "Point", "coordinates": [ -78.520205024151821, 8.988536919182696 ] } },
{ "type": "Feature", "properties": { "field_1": 772748.9755, "field_2": 994638.1216 }, "geometry": { "type": "Point", "coordinates": [ -78.519336011420492, 8.989714840526263 ] } },
{ "type": "Feature", "properties": { "field_1": 772755.3236, "field_2": 994627.4351 }, "geometry": { "type": "Point", "coordinates": [ -78.519278969912392, 8.989617882937637 ] } }
]
}
